GNNSubNet/GNNSubNet.py
GNNSubNet/GNN_paper.py
GNNSubNet/OMICS_workflow.py
GNNSubNet/PGExplainer.py
GNNSubNet/__init__.py
GNNSubNet/community_detection.py
GNNSubNet/dataset.py
GNNSubNet/edge_importance.py
GNNSubNet/features_computation.py
GNNSubNet/gnn_explainer.py
GNNSubNet/gnn_training_utils.py
GNNSubNet/gnnexplainer_sim.py
GNNSubNet/gnnexplainer_vanilla_sim.py
GNNSubNet/graph_dataset.py
GNNSubNet/graphcheb.py
GNNSubNet/graphcnn.py
GNNSubNet/mlp.py
GNNSubNet/s2vgraph.py
GNNSubNet/datasets/synthetic/FEATURES_synthetic.txt
GNNSubNet/datasets/synthetic/NETWORK_synthetic.txt
GNNSubNet/datasets/synthetic/TARGET_synthetic.txt
GNNSubNet/datasets/synthetic/communities.txt
GNNSubNet/datasets/synthetic/communities_scores.txt
GNNSubNet/datasets/synthetic/edge_index.txt
GNNSubNet/datasets/synthetic/edge_masks.txt
GNNSubNet/datasets/synthetic/gene_names.txt
GNNSubNet-0.2.1.dist-info/LICENSE
GNNSubNet-0.2.1.dist-info/METADATA
GNNSubNet-0.2.1.dist-info/WHEEL
GNNSubNet-0.2.1.dist-info/top_level.txt
GNNSubNet-0.2.1.dist-info/RECORD
